<?xml version="1.0" encoding="UTF-8"?>
<xqdoc:xqdoc xmlns:xqdoc="http://www.xqdoc.org/1.0">
    <xqdoc:control>
        <xqdoc:date>2015-07-13T10:52:23.411Z</xqdoc:date>
        <xqdoc:location>/db/apps/blumenbach/modules/filesize.xql</xqdoc:location>
    </xqdoc:control>
    <xqdoc:module type="library">
        <xqdoc:uri>http://exist-db.org/xquery/filesize</xqdoc:uri>
        <xqdoc:name>filesize</xqdoc:name>
        <xqdoc:comment>
            <xqdoc:description>
 Prefetches file size using curl
 
</xqdoc:description>
        </xqdoc:comment>
    </xqdoc:module>
    <xqdoc:functions>
        <xqdoc:function>
            <xqdoc:name>filesize:get-file-header</xqdoc:name>
            <xqdoc:signature>filesize:get-file-header($url as xs:string?) as item()*</xqdoc:signature>
            <xqdoc:comment>
                <xqdoc:description/>
                <xqdoc:param>$url? </xqdoc:param>
                <xqdoc:return>item()*</xqdoc:return>
            </xqdoc:comment>
        </xqdoc:function>
        <xqdoc:function>
            <xqdoc:name>filesize:get-size</xqdoc:name>
            <xqdoc:signature>filesize:get-size($url as xs:string) as item()*</xqdoc:signature>
            <xqdoc:comment>
                <xqdoc:description/>
                <xqdoc:param>$url </xqdoc:param>
                <xqdoc:return>item()*</xqdoc:return>
            </xqdoc:comment>
        </xqdoc:function>
    </xqdoc:functions>
</xqdoc:xqdoc>